bq/metadoc/__init__.py
bq/metadoc/etree.py
bq/metadoc/formats.py
bq/metadoc/version.py
bq/metadoc/xmldict.py
bisque_metadoc-0.6.6.1.dist-info/METADATA
bisque_metadoc-0.6.6.1.dist-info/WHEEL
bisque_metadoc-0.6.6.1.dist-info/top_level.txt
bisque_metadoc-0.6.6.1.dist-info/RECORD
