Metadata-Version: 2.4
Name: bisque_metadoc
Version: 0.6.6.1
Summary: Bisque Metadoc
Author-email: ViQi Inc <info@viqi.org>
Project-URL: homepage, https://gitlab.com/viqi/viqi-common/bisque_metadoc
Classifier: Programming Language :: Python :: 3
Classifier: Programming Language :: Python :: 3.8
Classifier: Programming Language :: Python :: 3.10
Requires-Python: >=3.8
Requires-Dist: python-mimeparse
Requires-Dist: simplejson
Requires-Dist: lxml
Requires-Dist: deprecated
